CHANGES.rst
CONTRIBUTORS.rst
MANIFEST.in
README.rst
setup.cfg
setup.py
docs/LICENSE.GPL
docs/LICENSE.rst
docs/index.rst
src/collective/__init__.py
src/collective.sgvizler.egg-info/PKG-INFO
src/collective.sgvizler.egg-info/SOURCES.txt
src/collective.sgvizler.egg-info/dependency_links.txt
src/collective.sgvizler.egg-info/entry_points.txt
src/collective.sgvizler.egg-info/namespace_packages.txt
src/collective.sgvizler.egg-info/not-zip-safe
src/collective.sgvizler.egg-info/requires.txt
src/collective.sgvizler.egg-info/top_level.txt
src/collective/sgvizler/__init__.py
src/collective/sgvizler/configure.zcml
src/collective/sgvizler/interfaces.py
src/collective/sgvizler/setuphandlers.py
src/collective/sgvizler/sparql_viz.py
src/collective/sgvizler/testing.py
src/collective/sgvizler/vocabularies.py
src/collective/sgvizler/browser/__init__.py
src/collective/sgvizler/browser/configure.zcml
src/collective/sgvizler/browser/overrides/.gitkeep
src/collective/sgvizler/browser/static/.gitkeep
src/collective/sgvizler/browser/static/d3.v2.min.js
src/collective/sgvizler/browser/static/gviz-api.js
src/collective/sgvizler/browser/static/raphael-dracula.min.js
src/collective/sgvizler/browser/static/sgvizler-setup.js
src/collective/sgvizler/browser/static/sgvizler.charts.css
src/collective/sgvizler/browser/static/sgvizler.datatable.pack.js
src/collective/sgvizler/browser/static/sgvizler.js
src/collective/sgvizler/browser/static/sgvizler.min.js
src/collective/sgvizler/browser/static/sgvizler.pack.js
src/collective/sgvizler/browser/static/sgvizler.visualization.pack.js
src/collective/sgvizler/locales/collective.sgvizler.pot
src/collective/sgvizler/locales/update.sh
src/collective/sgvizler/profiles/default/browserlayer.xml
src/collective/sgvizler/profiles/default/collectivesgvizler_default.txt
src/collective/sgvizler/profiles/default/cssregistry.xml
src/collective/sgvizler/profiles/default/jsregistry.xml
src/collective/sgvizler/profiles/default/metadata.xml
src/collective/sgvizler/profiles/default/types.xml
src/collective/sgvizler/profiles/default/types/sparqlviz.xml
src/collective/sgvizler/profiles/uninstall/browserlayer.xml
src/collective/sgvizler/profiles/uninstall/collectivesgvizler_uninstall.txt
src/collective/sgvizler/sparql_viz_templates/sampleview.pt
src/collective/sgvizler/tests/__init__.py
src/collective/sgvizler/tests/test_robot.py
