Metadata-Version: 1.1
Name: collective.sgvizler
Version: 1.0.1
Summary: SGVizler integration for Plone 4
Home-page: https://pypi.python.org/pypi/collective.sgvizler
Author: Encolpe DEGOUTE
Author-email: encolpe.degoute@free.fr
License: GPL version 2
Keywords: Python Plone
Platform: UNKNOWN
Classifier: Environment :: Web Environment
Classifier: Framework :: Plone
Classifier: Framework :: Plone :: 5.0
Classifier: Framework :: Plone :: 4.3
Classifier: Programming Language :: Python
Classifier: Programming Language :: Python :: 2.7
Classifier: Operating System :: OS Independent
Classifier: License :: OSI Approved :: GNU General Public License v2 (GPLv2)
